grievios/__init__.py
grievios/analyzers/__init__.py
grievios/analyzers/exploration_analyzer.py
grievios/analyzers/ios/__init__.py
grievios/analyzers/ios/ios_analyzer.py
grievios/analyzers/ios/mitmdump.py
grievios/analyzers/ios/tcpdump.py
grievios/common.py
grievios/crud.py
grievios/database.py
grievios/exploration/__init__.py
grievios/exploration/exploration_session.py
grievios/exploration/exploration_session_options.py
grievios/exploration/exploration_worker.py
grievios/main.py
grievios/models.py
grievios/schemas.py
grievios/strategies/__init__.py
grievios/strategies/exploration_strategy.py
grievios/strategies/ios/__init__.py
grievios/strategies/ios/idle.py
grievios/strategies/ios/ios_strategy.py
grievios/strategies/ios/random_button.py
grievios/utils/__init__.py
grievios/utils/cmdline_utils/__init__.py
grievios/utils/cmdline_utils/cmdline_util.py
grievios/utils/cmdline_utils/ideviceid.py
grievios/utils/cmdline_utils/ideviceinfo.py
grievios/utils/cmdline_utils/ideviceinstaller.py
grievios/utils/cmdline_utils/mitmdump.py
grievios/utils/cmdline_utils/rvictl.py
grievios/utils/cmdline_utils/tcpdump.py
grievios/utils/ipa.py
grievios/web/__init__.py
grievios/web/dependencies.py
grievios/web/routers/__init__.py
grievios/web/routers/appium_servers.py
grievios/web/routers/devices.py
grievios/web/routers/explorations.py
grievios/web/static/alpine.min.js
grievios/web/static/icons/alert-circle.svg
grievios/web/static/icons/check-circle.svg
grievios/web/static/icons/check-square.svg
grievios/web/static/icons/edit.svg
grievios/web/static/icons/skip-back.svg
grievios/web/static/icons/trash-2.svg
grievios/web/static/icons/trash.svg
grievios/web/static/icons/x-circle.svg
grievios/web/static/icons/x-square.svg
grievios/web/static/pico.min.css
grievios/web/static/pico.min.css.map
grievios/web/templates/appium-servers.html
grievios/web/templates/base.html
grievios/web/templates/devices.html
grievios/web/templates/explorations.html
grievios/web/templates/index.html
grievios-0.1.0.dist-info/METADATA
grievios-0.1.0.dist-info/WHEEL
grievios-0.1.0.dist-info/entry_points.txt
grievios-0.1.0.dist-info/RECORD
