Metadata-Version: 2.1
Name: grievios
Version: 0.1.0
Summary: 
Author: Hannes Hauer
Author-email: grievios@hanneshauer.eu
Requires-Python: >=3.10,<4.0
Classifier: Programming Language :: Python :: 3
Classifier: Programming Language :: Python :: 3.10
Classifier: Programming Language :: Python :: 3.11
Requires-Dist: appium-python-client (>=2.10.1,<3.0.0)
Requires-Dist: fastapi (>=0.95.2,<0.96.0)
Requires-Dist: jinja2 (>=3.1.2,<4.0.0)
Requires-Dist: networkx (>=3.1,<4.0)
Requires-Dist: sqlalchemy (>=2.0.15,<3.0.0)
Requires-Dist: uvicorn[standard] (>=0.22.0,<0.23.0)
